hello_linker/__init__.py
hello_linker/kaminet.py
HelloLinker-1.1.dist-info/METADATA
HelloLinker-1.1.dist-info/WHEEL
HelloLinker-1.1.dist-info/top_level.txt
HelloLinker-1.1.dist-info/RECORD
